tuplehash.py
tuplehash-0.1.0a2.dist-info/licenses/LICENSE
tuplehash-0.1.0a2.dist-info/METADATA
tuplehash-0.1.0a2.dist-info/WHEEL
tuplehash-0.1.0a2.dist-info/top_level.txt
tuplehash-0.1.0a2.dist-info/RECORD
