Metadata-Version: 2.4
Name: tuplehash
Version: 0.1.0a2
Summary: Pure Python reimplementation of CPython's `tuplehash` function with exact overflow behavior, designed for hashing user-defined immutable sequences.
Author-email: Jifeng Wu <jifengwu2k@gmail.com>
License-Expression: MIT
Project-URL: Homepage, https://github.com/jifengwu2k/tuplehash
Project-URL: Bug Tracker, https://github.com/jifengwu2k/tuplehash/issues
Classifier: Programming Language :: Python :: 2
Classifier: Programming Language :: Python :: 3
Classifier: Operating System :: OS Independent
Requires-Python: >=2
License-File: LICENSE
Requires-Dist: fixed-width-int
Requires-Dist: typing; python_version < "3.5"
Dynamic: license-file
